odoo/addons/account_cash_deposit/README.rst
odoo/addons/account_cash_deposit/__init__.py
odoo/addons/account_cash_deposit/__manifest__.py
odoo/addons/account_cash_deposit/data/cash_unit_cad.xml
odoo/addons/account_cash_deposit/data/cash_unit_chf.xml
odoo/addons/account_cash_deposit/data/cash_unit_eur.xml
odoo/addons/account_cash_deposit/data/cash_unit_usd.xml
odoo/addons/account_cash_deposit/data/sequence.xml
odoo/addons/account_cash_deposit/i18n/account_cash_deposit.pot
odoo/addons/account_cash_deposit/i18n/es.po
odoo/addons/account_cash_deposit/i18n/fr.po
odoo/addons/account_cash_deposit/i18n/hr.po
odoo/addons/account_cash_deposit/i18n/it.po
odoo/addons/account_cash_deposit/models/__init__.py
odoo/addons/account_cash_deposit/models/account_cash_deposit.py
odoo/addons/account_cash_deposit/models/cash_unit.py
odoo/addons/account_cash_deposit/models/res_currency.py
odoo/addons/account_cash_deposit/readme/CONFIGURE.md
odoo/addons/account_cash_deposit/readme/CONTRIBUTORS.md
odoo/addons/account_cash_deposit/readme/DESCRIPTION.md
odoo/addons/account_cash_deposit/readme/USAGE.md
odoo/addons/account_cash_deposit/report/report.xml
odoo/addons/account_cash_deposit/report/report_cashdeposit.xml
odoo/addons/account_cash_deposit/security/ir.model.access.csv
odoo/addons/account_cash_deposit/security/security.xml
odoo/addons/account_cash_deposit/static/description/cash_deposit_form.png
odoo/addons/account_cash_deposit/static/description/currency_form_view.png
odoo/addons/account_cash_deposit/static/description/icon.png
odoo/addons/account_cash_deposit/static/description/index.html
odoo/addons/account_cash_deposit/tests/__init__.py
odoo/addons/account_cash_deposit/tests/test_cash_deposit.py
odoo/addons/account_cash_deposit/views/account_cash_deposit.xml
odoo/addons/account_cash_deposit/views/cash_unit.xml
odoo/addons/account_cash_deposit/views/res_currency.xml
odoo/addons/account_cash_deposit/wizards/__init__.py
odoo_addon_account_cash_deposit-18.0.1.0.0.6.dist-info/METADATA
odoo_addon_account_cash_deposit-18.0.1.0.0.6.dist-info/WHEEL
odoo_addon_account_cash_deposit-18.0.1.0.0.6.dist-info/top_level.txt
odoo_addon_account_cash_deposit-18.0.1.0.0.6.dist-info/RECORD
